README.md
jsonpyth.py
setup.py
JSONPyth.egg-info/PKG-INFO
JSONPyth.egg-info/SOURCES.txt
JSONPyth.egg-info/dependency_links.txt
JSONPyth.egg-info/requires.txt
JSONPyth.egg-info/top_level.txt