Metadata-Version: 2.1
Name: JSONPyth
Version: 0.1.3
Summary: A JSONPath implementation for Python
Home-page: https://github.com/Frimkron/JSONPyth
Author: Mark Frimston
Author-email: mfrimston@gmail.com
License: MIT
Keywords: json jsonpath xpath query
Platform: UNKNOWN
Classifier: Programming Language :: Python :: 3 :: Only
Classifier: License :: OSI Approved :: MIT License
Classifier: Operating System :: OS Independent
Requires-Python: >=3.5
